Circuit_B/Circuit_B.v
module Circuit_B (F1, F2, F3, A0, A1, B0, B1);
    output F1, F2, F3;
    input A0, A1, B0, B1;
    nor (F1, F2, F3);
    or (F2, w1, w2, w3);
    and (F3, w4, w5);
    and (w1, w6, B1);
    or (w2, w6, w7, B0);
    and (w3, w7, B0, B1);
    not (w6, A1);
    not (w7, A0);
    xor (w4, A1, B1);
    xnor (w5, A0, B0);
endmodule

Circuit_B/Circuit_B_tb.v
`timescale 1ns/1ps
`include "Circuit_B.v"

module Circuit_B_tb;
    reg A0, A1, B0, B1;
    wire F1, F2, F3;

    Circuit_B M_UUT (F1, F2, F3, A0, A1, B0, B1);

    initial begin
        $dumpfile("Circuit_B.vcd");
        $dumpvars(0, Circuit_B_tb);
        A0 = 0; A1 = 0; B0 = 0; B1 = 0;
        #100 A0 = 0; A1 = 0; B0 = 0; B1 = 1;
        #100 A0 = 0; A1 = 0; B0 = 1; B1 = 0;
        #100 A0 = 0; A1 = 0; B0 = 1; B1 = 1;
        #100 A0 = 0; A1 = 1; B0 = 0; B1 = 0;
        #100 A0 = 0; A1 = 1; B0 = 0; B1 = 1;
        #100 A0 = 0; A1 = 1; B0 = 1; B1 = 0;
        #100 A0 = 0; A1 = 1; B0 = 1; B1 = 1;
        #100 A0 = 1; A1 = 0; B0 = 0; B1 = 1;
        #100 A0 = 1; A1 = 0; B0 = 1; B1 = 0;
        #100 A0 = 1; A1 = 0; B0 = 1; B1 = 1;
        #100 A0 = 1; A1 = 1; B0 = 0; B1 = 0;
        #100 A0 = 1; A1 = 1; B0 = 0; B1 = 1;
        #100 A0 = 1; A1 = 1; B0 = 1; B1 = 0;
        #100 A0 = 1; A1 = 1; B0 = 1; B1 = 1;
        #100 $finish;
    end
endmodule

Circuit_B/Circuit_B.vcd
$date
	Wed Nov 06 18:58:36 2024
$end
$version
	Icarus Verilog
$end
$timescale
	1ps
$end
$scope module Circuit_B_tb $end
$var wire 1 ! F3 $end
$var wire 1 " F2 $end
$var wire 1 # F1 $end
$var reg 1 $ A0 $end
$var reg 1 % A1 $end
$var reg 1 & B0 $end
$var reg 1 ' B1 $end
$scope module M_UUT $end
$var wire 1 $ A0 $end
$var wire 1 % A1 $end
$var wire 1 & B0 $end
$var wire 1 ' B1 $end
$var wire 1 # F1 $end
$var wire 1 " F2 $end
$var wire 1 ! F3 $end
$var wire 1 ( w1 $end
$var wire 1 ) w2 $end
$var wire 1 * w3 $end
$var wire 1 + w4 $end
$var wire 1 , w5 $end
$var wire 1 - w6 $end
$var wire 1 . w7 $end
$upscope $end
$upscope $end
$enddefinitions $end
$comment Show the parameter values. $end
$dumpall
$end
#0
$dumpvars
1.
1-
1,
0+
0*
1)
0(
0'
0&
0%
0$
0#
1"
0!
$end
#100000
1!
1(
1+
1'
#200000
0!
0(
0+
0,
0'
1&
#300000
1(
1*
1+
1'
#400000
1!
0(
0*
1,
0-
0'
0&
1%
#500000
0!
0+
1'
#600000
1+
0,
0'
1&
#700000
1*
0+
1'
#800000
1(
0*
1-
1+
0.
0&
0%
1$
#900000
0(
0+
1,
0'
1&
#1000000
1!
1(
1+
1'
#1100000
1#
0"
0!
0(
0)
0,
0-
0'
0&
1%
#1200000
0+
1'
#1300000
0#
1"
1!
1+
1)
1,
0'
1&
#1400000
0!
0+
1'
