Circuit_Boolean_CA/Circuit_Boolean_CA.v
module Circuit_Boolean_CA (
    input A, B, C, D,
    output E, F
);
    
    assign E = A | (B && C) | ((!B) && D);
    assign F = ((!B) && C) | (B & (!C) && (!D));
endmodule

Circuit_Boolean_CA/Circuit_Boolean_CA_tb.v
`timescale 1ns/1ps
`include "Circuit_Boolean_CA.v"

module Circuit_Boolean_CA_tb;
    reg A, B, C, D;
    wire E, F;

    Circuit_Boolean_CA M_UUT (A, B, C, D, E, F);

    initial begin
        $dumpfile("Circuit_Boolean_CA.vcd");
        $dumpvars(0, Circuit_Boolean_CA_tb);
        A = 0; B = 0; C = 0; D = 0;
        #100 A = 0; B = 0; C = 0; D = 1;
        #100 A = 0; B = 0; C = 1; D = 0;
        #100 A = 0; B = 0; C = 1; D = 1;
        #100 A = 0; B = 1; C = 0; D = 0;
        #100 A = 0; B = 1; C = 0; D = 1;
        #100 A = 0; B = 1; C = 1; D = 0;
        #100 A = 0; B = 1; C = 1; D = 1;
        #100 A = 1; B = 0; C = 0; D = 1;
        #100 A = 1; B = 0; C = 1; D = 0;
        #100 A = 1; B = 0; C = 1; D = 1;
        #100 A = 1; B = 1; C = 0; D = 0;
        #100 A = 1; B = 1; C = 0; D = 1;
        #100 A = 1; B = 1; C = 1; D = 0;
        #100 A = 1; B = 1; C = 1; D = 1;
        #100 $finish;
    end
endmodule

Circuit_Boolean_CA/Circuit_Boolean_CA.vcd
$date
	Wed Nov 06 16:56:10 2024
$end
$version
	Icarus Verilog
$end
$timescale
	1ps
$end
$scope module Circuit_Boolean_CA_tb $end
$var wire 1 ! F $end
$var wire 1 " E $end
$var reg 1 # A $end
$var reg 1 $ B $end
$var reg 1 % C $end
$var reg 1 & D $end
$scope module M_UUT $end
$var wire 1 # A $end
$var wire 1 $ B $end
$var wire 1 % C $end
$var wire 1 & D $end
$var wire 1 " E $end
$var wire 1 ! F $end
$upscope $end
$upscope $end
$enddefinitions $end
$comment Show the parameter values. $end
$dumpall
$end
#0
$dumpvars
0&
0%
0$
0#
0"
0!
$end
#100000
1"
1&
#200000
0"
1!
0&
1%
#300000
1"
1&
#400000
0"
0&
0%
1$
#500000
0!
1&
#600000
1"
0&
1%
#700000
1&
#800000
0%
0$
1#
#900000
1!
0&
1%
#1000000
1&
#1100000
0&
0%
1$
#1200000
0!
1&
#1300000
0&
1%
#1400000
1&
