UDP_02467/Circuit_with_UDP_02467.v
primitive UDP_02467 (D, A, B, C);
    output D;
    input A, B, C;
    //Truth table for D = f (A, B, C) = ∑(0, 2, 4, 6, 7);
    table
        //A B C : D
        0 0 0 : 1;
        0 0 1 : 0;
        0 1 0 : 1;
        0 1 1 : 0;
        1 0 0 : 1;
        1 0 1 : 0;
        1 1 0 : 1;
        1 1 1 : 1;
    endtable
endprimitive

module Circuit_with_UDP_02467 (
    output E, F,
    input A, B, C, D
);
    UDP_02467 (E, A, B, C);  //把結果給e(因為UDP_02467說第一個是output)
    and (F, E, D);
endmodule

UDP_02467/Circuit_with_UDP_02467_tb.v
`timescale 1ns/1ps
`include "Circuit_with_UDP_02467.v"

module Circuit_with_UDP_02467_tb;
    reg A, B, C, D;
    wire E, F;
    
    Circuit_with_UDP_02467 M_UUT (E, F, A, B, C, D);

    initial begin
        $dumpfile("Circuit_with_UDP_02467.vcd");
        $dumpvars(0, Circuit_with_UDP_02467_tb);
        A = 0; B = 0; C = 0; D = 0;
        #100 A = 0; B = 0; C = 0; D = 1;
        #100 A = 0; B = 0; C = 1; D = 0;
        #100 A = 0; B = 0; C = 1; D = 1;
        #100 A = 0; B = 1; C = 0; D = 0;
        #100 A = 0; B = 1; C = 0; D = 1;
        #100 A = 0; B = 1; C = 1; D = 0;
        #100 A = 0; B = 1; C = 1; D = 1;
        #100 A = 1; B = 0; C = 0; D = 1;
        #100 A = 1; B = 0; C = 1; D = 0;
        #100 A = 1; B = 0; C = 1; D = 1;
        #100 A = 1; B = 1; C = 0; D = 0;
        #100 A = 1; B = 1; C = 0; D = 1;
        #100 A = 1; B = 1; C = 1; D = 0;
        #100 A = 1; B = 1; C = 1; D = 1;
        #100 $finish;
    end
endmodule

UDP_02467/Circuit_with_UDP_02467.vcd
$date
	Wed Nov 06 18:00:55 2024
$end
$version
	Icarus Verilog
$end
$timescale
	1ps
$end
$scope module Circuit_with_UDP_02467_tb $end
$var wire 1 ! F $end
$var wire 1 " E $end
$var reg 1 # A $end
$var reg 1 $ B $end
$var reg 1 % C $end
$var reg 1 & D $end
$scope module M_UUT $end
$var wire 1 # A $end
$var wire 1 $ B $end
$var wire 1 % C $end
$var wire 1 & D $end
$var wire 1 " E $end
$var wire 1 ! F $end
$upscope $end
$upscope $end
$enddefinitions $end
$comment Show the parameter values. $end
$dumpall
$end
#0
$dumpvars
0&
0%
0$
0#
1"
0!
$end
#100000
1!
1&
#200000
0!
0"
0&
1%
#300000
1&
#400000
1"
0&
0%
1$
#500000
1!
1&
#600000
0!
0"
0&
1%
#700000
1&
#800000
1!
1"
0%
0$
1#
#900000
0!
0"
0&
1%
#1000000
1&
#1100000
1"
0&
0%
1$
#1200000
1!
1&
#1300000
0!
0&
1%
#1400000
1!
1&
