or_and/or_and.v
module or_and (
    input A, B, C,
    output E
);
    wire D;
    assign D = A | B;
    assign E = C & D;
endmodule

or_and/or_and_tb.v
`timescale 1ns/1ps
`include "or_and.v"

module or_and_tb;
    reg A, B, C;
    wire E;

    or_and M_UUT (A, B, C, E);

    initial begin
        $dumpfile("or_and.vcd");
        $dumpvars(0, or_and_tb);
        A = 0; B = 0; C = 0;
        #100 A = 0; B = 0; C = 1;
        #100 A = 0; B = 1; C = 0;
        #100 A = 0; B = 1; C = 1;
        #100 A = 1; B = 0; C = 0;
        #100 A = 1; B = 0; C = 1;
        #100 A = 1; B = 1; C = 0;
        #100 A = 1; B = 1; C = 1;
        #100 $finish;
    end
endmodule

or_and/or_and.vcd
$date
	Wed Nov 06 16:43:21 2024
$end
$version
	Icarus Verilog
$end
$timescale
	1ps
$end
$scope module or_and_tb $end
$var wire 1 ! E $end
$var reg 1 " A $end
$var reg 1 # B $end
$var reg 1 $ C $end
$scope module M_UUT $end
$var wire 1 " A $end
$var wire 1 # B $end
$var wire 1 $ C $end
$var wire 1 % D $end
$var wire 1 ! E $end
$upscope $end
$upscope $end
$enddefinitions $end
$comment Show the parameter values. $end
$dumpall
$end
#0
$dumpvars
0%
0$
0#
0"
0!
$end
#100000
1$
#200000
1%
0$
1#
#300000
1!
1$
#400000
0!
0$
0#
1"
#500000
1!
1$
#600000
0!
0$
1#
#700000
1!
1$
